hatch_mypyc/__about__.py
hatch_mypyc/__init__.py
hatch_mypyc/hooks.py
hatch_mypyc/plugin.py
hatch_mypyc/utils.py
hatch_mypyc-0.16.0.dist-info/METADATA
hatch_mypyc-0.16.0.dist-info/WHEEL
hatch_mypyc-0.16.0.dist-info/entry_points.txt
hatch_mypyc-0.16.0.dist-info/licenses/LICENSE.txt
hatch_mypyc-0.16.0.dist-info/RECORD
