Metadata-Version: 2.1
Name: hatch-mypyc
Version: 0.16.0
Summary: Hatch build hook plugin for Mypyc
Project-URL: Funding, https://github.com/sponsors/ofek
Project-URL: History, https://github.com/ofek/hatch-mypyc/blob/master/HISTORY.md
Project-URL: Issues, https://github.com/ofek/hatch-mypyc/issues
Project-URL: Source, https://github.com/ofek/hatch-mypyc
Author-email: Ofek Lev <oss@ofek.dev>
License-Expression: MIT
License-File: LICENSE.txt
Keywords: build,hatch,mypy,mypyc,plugin,typing
Classifier: Development Status :: 4 - Beta
Classifier: Framework :: Hatch
Classifier: License :: OSI Approved :: MIT License
Classifier: Programming Language :: Python
Classifier: Programming Language :: Python :: 3.7
Classifier: Programming Language :: Python :: 3.8
Classifier: Programming Language :: Python :: 3.9
Classifier: Programming Language :: Python :: 3.10
Classifier: Programming Language :: Python :: 3.11
Classifier: Programming Language :: Python :: Implementation :: CPython
Classifier: Programming Language :: Python :: Implementation :: PyPy
Classifier: Topic :: Software Development :: Build Tools
Requires-Python: >=3.7
Requires-Dist: hatchling>=1.12.2
Requires-Dist: mypy>=0.971
Requires-Dist: pathspec
Requires-Dist: setuptools
